MysqlChaoXinshourumen/README.md
MysqlChaoXinshourumen/__init__.py
MysqlChaoXinshourumen/__main__.py
MysqlChaoXinshourumen/file.epub
MysqlChaoXinshourumen/index.html
MysqlChaoXinshourumen/css/__init__.py
MysqlChaoXinshourumen/css/annotations.css
MysqlChaoXinshourumen/css/main.css
MysqlChaoXinshourumen/css/normalize.css
MysqlChaoXinshourumen/css/popup.css
MysqlChaoXinshourumen/font/__init__.py
MysqlChaoXinshourumen/font/fontello.eot
MysqlChaoXinshourumen/font/fontello.svg
MysqlChaoXinshourumen/font/fontello.ttf
MysqlChaoXinshourumen/font/fontello.woff
MysqlChaoXinshourumen/img/__init__.py
MysqlChaoXinshourumen/img/annotator-glyph-sprite.png
MysqlChaoXinshourumen/img/annotator-icon-sprite.png
MysqlChaoXinshourumen/img/apple-touch-icon.png
MysqlChaoXinshourumen/img/cancelfullscreen.png
MysqlChaoXinshourumen/img/close.png
MysqlChaoXinshourumen/img/fullscreen.png
MysqlChaoXinshourumen/img/loader.gif
MysqlChaoXinshourumen/img/menu-icon.png
MysqlChaoXinshourumen/img/save.png
MysqlChaoXinshourumen/img/saved.png
MysqlChaoXinshourumen/img/settings-s.png
MysqlChaoXinshourumen/img/settings.png
MysqlChaoXinshourumen/img/star.png
MysqlChaoXinshourumen/js/__init__.py
MysqlChaoXinshourumen/js/epub.js
MysqlChaoXinshourumen/js/epub.min.js
MysqlChaoXinshourumen/js/epub.min.map
MysqlChaoXinshourumen/js/hooks.min.js
MysqlChaoXinshourumen/js/hooks.min.map
MysqlChaoXinshourumen/js/reader.js
MysqlChaoXinshourumen/js/reader.js.map
MysqlChaoXinshourumen/js/reader.min.js
MysqlChaoXinshourumen/js/reader.min.map
MysqlChaoXinshourumen/js/hooks/__init__.py
MysqlChaoXinshourumen/js/hooks/extensions/__init__.py
MysqlChaoXinshourumen/js/hooks/extensions/highlight.js
MysqlChaoXinshourumen/js/libs/__init__.py
MysqlChaoXinshourumen/js/libs/jquery.min.js
MysqlChaoXinshourumen/js/libs/localforage.min.js
MysqlChaoXinshourumen/js/libs/screenfull.js
MysqlChaoXinshourumen/js/libs/screenfull.min.js
MysqlChaoXinshourumen/js/libs/zip.min.js
MysqlChaoXinshourumen/js/plugins/__init__.py
mysql_chao_xinshourumen-2024.3.2.0.dist-info/METADATA
mysql_chao_xinshourumen-2024.3.2.0.dist-info/WHEEL
mysql_chao_xinshourumen-2024.3.2.0.dist-info/entry_points.txt
mysql_chao_xinshourumen-2024.3.2.0.dist-info/top_level.txt
mysql_chao_xinshourumen-2024.3.2.0.dist-info/RECORD
